django_admin_settings/__init__.py
django_admin_settings/admin.py
django_admin_settings/apps.py
django_admin_settings/text_input_filter.py
django_admin_settings/extras/__init__.py
django_admin_settings/extras/get_admin_models.py
django_admin_settings/extras/get_class_from_module.py
django_admin_settings/forms/__init__.py
django_admin_settings/forms/model_choices_form.py
django_admin_settings/migrations/0001_list_display.py
django_admin_settings/migrations/0002_list_display_link.py
django_admin_settings/migrations/0003_list_filter.py
django_admin_settings/migrations/__init__.py
django_admin_settings/models/__init__.py
django_admin_settings/models/list_display.py
django_admin_settings/models/list_display_link.py
django_admin_settings/models/list_filter.py
django_admin_settings/templates/django_admin_settings/text_input_filter/form.html
django_admin_settings-0.4.1.dist-info/LICENSE
django_admin_settings-0.4.1.dist-info/METADATA
django_admin_settings-0.4.1.dist-info/WHEEL
django_admin_settings-0.4.1.dist-info/top_level.txt
django_admin_settings-0.4.1.dist-info/RECORD
